liberty/__init__.py
liberty/arrays.py
liberty/boolean_functions.py
liberty/parser.py
liberty/types.py
liberty_parser-0.0.4.dist-info/LICENSE
liberty_parser-0.0.4.dist-info/METADATA
liberty_parser-0.0.4.dist-info/WHEEL
liberty_parser-0.0.4.dist-info/top_level.txt
liberty_parser-0.0.4.dist-info/RECORD
